pyconus_test4/__init__.py
pyconus_test4/__main__.py
pyconus_test4-0.0.2.data/scripts/hello
pyconus_test4-0.0.2.dist-info/METADATA
pyconus_test4-0.0.2.dist-info/WHEEL
pyconus_test4-0.0.2.dist-info/entry_points.txt
pyconus_test4-0.0.2.dist-info/top_level.txt
pyconus_test4-0.0.2.dist-info/RECORD
