Metadata-Version: 2.1
Name: pyconus-test4
Version: 0.0.2
Summary: short
Home-page: https://google.com
Author: Cole Wilson
Author-email: cole@colewilson.xyz
License: none
Keywords: kw1 kw2
Platform: UNKNOWN
Classifier: Programming Language :: Python :: 3
Requires-Python: >=3.6
